linedify/__init__.py
linedify/dify.py
linedify/integration.py
linedify/session.py
linedify-0.3.5.dist-info/LICENSE
linedify-0.3.5.dist-info/METADATA
linedify-0.3.5.dist-info/WHEEL
linedify-0.3.5.dist-info/top_level.txt
linedify-0.3.5.dist-info/RECORD
