Metadata-Version: 2.1
Name: linedify
Version: 0.3.5
Summary: 💬⚡ linedify: Supercharging your LINE Bot with Dify power!
Home-page: https://github.com/uezo/linedify
Author: uezo
Author-email: uezo@uezo.net
Maintainer: uezo
Maintainer-email: uezo@uezo.net
License: Apache v2
Classifier: Programming Language :: Python :: 3
License-File: LICENSE
Requires-Dist: aiohttp >=3.9.5
Requires-Dist: line-bot-sdk >=3.11.0
Requires-Dist: fastapi >=0.111.0
Requires-Dist: uvicorn >=0.30.1
Requires-Dist: SQLAlchemy >=2.0.31
